{"title":"ERA Aljezur","url":"https://www.era.pt/en/buy?ob=1&tp=1,2&lc=08-03&page=1&ord=3","favicon":"https://www.era.pt/Portals/_default/Skins/ERA/webmanifest/favicon-32x32.png","elements":[{"title":"290.000 € Odeceixe, Faro","contents":"House T2 Aljezur, Odeceixe - 1465432 - 10 Odeceixe, Faro House 228570189","link":"https://www.era.pt/en/property/house-t2-aljezur-odeceixe-411250014","retrieved":1747158005973},{"title":"850.000 € Aljezur, Faro","contents":"Urban Plot  Aljezur - 1475659 - 20 Aljezur, Faro House 452772777943","link":"https://www.era.pt/en/property/house-t4-aljezur-411250013","retrieved":1744911521225},{"title":"418.000 € Espartal, Aljezur","contents":"Terraced House T3 com Swimming pool Aljezur, Espartal - 1464245 - 8 Espartal, Aljezur Terraced House 33166166371","link":"https://www.era.pt/en/property/terraced-house-t3-swimming-pool-aljezur-espartal-411250011","retrieved":1742406059440},{"title":"266.000 € Rogil, Faro","contents":"Terraced House T1 Aljezur, Rogil - 1465440 - 13 Rogil, Faro Terraced House 11110150150","link":"https://www.era.pt/en/property/terraced-house-t1-aljezur-rogil-411250009","retrieved":1741023471502},{"title":"499.995 € Aljezur, Faro","contents":"House T3 Aljezur - 1463249 - 22 Aljezur, Faro House 32179648","link":"https://www.era.pt/en/property/house-t3-aljezur-411250008","retrieved":1741023471504},{"title":"270.000 € Espartal, Aljezur","contents":"Apartment T2 Aljezur, Espartal - 1457611 - 4 Espartal, Aljezur Apartment 2284841","link":"https://www.era.pt/en/property/apartment-t2-furnished-aljezur-espartal-411250007","retrieved":1741973720508},{"title":"Upon Request Odeceixe, Aljezur","contents":"Apartment T1 Aljezur, Odeceixe - 1451568 - 10 Odeceixe, Aljezur Apartment 11565620","link":"https://www.era.pt/en/property/apartment-t1-aljezur-odeceixe-411250002","retrieved":1741023471508},{"title":"750.000 € Vale da Telha, Aljezur","contents":"House T6 Aljezur, Vale da Telha - 1451804 - 20 Vale da Telha, Aljezur House 6425025012503","link":"https://www.era.pt/en/property/house-t6-swimming-pool-aljezur-vale-da-telha-411250001","retrieved":1741023471510},{"title":"298.000 € Odeceixe, Aljezur","contents":"House T2 Aljezur, Odeceixe - 1439080 - 2 Odeceixe, Aljezur House 21847642","link":"https://www.era.pt/en/property/house-t2-aljezur-odeceixe-411240076","retrieved":1741023471512},{"title":"425.000 € Vale da Telha, Aljezur","contents":"Detached House T2 Aljezur, Vale da Telha - 1442803 - 19 Vale da Telha, Aljezur Detached House 211181188501","link":"https://www.era.pt/en/property/detached-house-t2-aljezur-vale-da-telha-411240073","retrieved":1741023471514},{"title":"1.275.000 € Vale da Telha, Aljezur","contents":"Apartment Floor Dwelling T6 Aljezur, Vale da Telha - 1432575 - 3 Vale da Telha, Aljezur House 6444844810004","link":"https://www.era.pt/en/property/house-t6-aljezur-vale-da-telha-411240050","retrieved":1741023471519},{"title":"Upon Request Aljezur, Faro","contents":"Apartment Floor Dwelling T2 Aljezur - 1432305 - 4 Aljezur, Faro House 203333169","link":"https://www.era.pt/en/property/house-t2-aljezur-411240049","retrieved":1741023471521},{"title":"350.000 € Odeceixe, Aljezur","contents":"Detached House T2 Aljezur, Odeceixe - 1426814 - 5 Odeceixe, Aljezur Detached House 218080200","link":"https://www.era.pt/en/property/detached-house-t2-aljezur-odeceixe-411240048","retrieved":1741023471522},{"title":"Upon Request Aldeia Antiga (Castelo), Aljezur","contents":"Terraced House T3 Aljezur, Aldeia Antiga (Castelo) - 1426683 - 27 Aldeia Antiga (Castelo), Aljezur Terraced House 36988","link":"https://www.era.pt/en/property/terraced-house-t3-aljezur-aldeia-antiga-castelo-411240047","retrieved":1741023471524},{"title":"275.000 € Bordeira, Faro","contents":"Apartment Floor Dwelling T2 Aljezur, Bordeira - 1424113 - 2 Bordeira, Faro Semi-Detached House 229898","link":"https://www.era.pt/en/property/semi-detached-house-t2-aljezur-bordeira-411240035","retrieved":1743788272899}]}